ethicrawl/__init__.py
ethicrawl/ethicrawl.py
ethicrawl/client/__init__.py
ethicrawl/client/client.py
ethicrawl/client/request.py
ethicrawl/client/response.py
ethicrawl/client/transport.py
ethicrawl/client/http/__init__.py
ethicrawl/client/http/chrome_transport.py
ethicrawl/client/http/http_client.py
ethicrawl/client/http/http_request.py
ethicrawl/client/http/http_response.py
ethicrawl/client/http/requests_transport.py
ethicrawl/config/__init__.py
ethicrawl/config/base_config.py
ethicrawl/config/concurrency_config.py
ethicrawl/config/config.py
ethicrawl/config/http_config.py
ethicrawl/config/http_proxy_config.py
ethicrawl/config/logger_config.py
ethicrawl/config/sitemap_config.py
ethicrawl/context/__init__.py
ethicrawl/context/asynchronous_client.py
ethicrawl/context/context.py
ethicrawl/context/context_manager.py
ethicrawl/context/queue.py
ethicrawl/context/synchronous_client.py
ethicrawl/context/target_context.py
ethicrawl/core/__init__.py
ethicrawl/core/headers.py
ethicrawl/core/resource.py
ethicrawl/core/resource_list.py
ethicrawl/core/url.py
ethicrawl/error/__init__.py
ethicrawl/error/domain_resolution_error.py
ethicrawl/error/domain_whitelist_error.py
ethicrawl/error/ethicrawl_error.py
ethicrawl/error/robot_error.py
ethicrawl/error/sitemap_error.py
ethicrawl/functions/__init__.py
ethicrawl/functions/validate_resource.py
ethicrawl/logger/__init__.py
ethicrawl/logger/color_formatter.py
ethicrawl/logger/logger.py
ethicrawl/robots/__init__.py
ethicrawl/robots/robot.py
ethicrawl/robots/robot_factory.py
ethicrawl/robots/robotochan.py
ethicrawl/sitemaps/__init__.py
ethicrawl/sitemaps/const.py
ethicrawl/sitemaps/index_document.py
ethicrawl/sitemaps/index_entry.py
ethicrawl/sitemaps/sitemap_document.py
ethicrawl/sitemaps/sitemap_entry.py
ethicrawl/sitemaps/sitemap_parser.py
ethicrawl/sitemaps/urlset_document.py
ethicrawl/sitemaps/urlset_entry.py
ethicrawl-1.0.0b2.dist-info/licenses/LICENSE
ethicrawl-1.0.0b2.dist-info/METADATA
ethicrawl-1.0.0b2.dist-info/WHEEL
ethicrawl-1.0.0b2.dist-info/top_level.txt
ethicrawl-1.0.0b2.dist-info/RECORD
