Metadata-Version: 2.4
Name: ethicrawl
Version: 1.0.0b2
Summary: A Python library for ethical web crawling
Author-email: Ethicrawl Team <ethicrawl@smkd.net>
License-Expression: Apache-2.0
Project-URL: Homepage, https://github.com/ethicrawl/ethicrawl
Project-URL: Documentation, https://ethicrawl.github.io/ethicrawl/
Project-URL: Repository, https://github.com/ethicrawl/ethicrawl
Keywords: web crawler,ethical,robots.txt,sitemap,web scraping
Classifier: Development Status :: 4 - Beta
Classifier: Intended Audience :: Developers
Classifier: Programming Language :: Python :: 3
Classifier: Programming Language :: Python :: 3.10
Classifier: Programming Language :: Python :: 3.11
Classifier: Programming Language :: Python :: 3.12
Classifier: Programming Language :: Python :: 3.13
Classifier: Topic :: Internet :: WWW/HTTP
Classifier: Topic :: Software Development :: Libraries
Classifier: Topic :: Software Development :: Libraries :: Python Modules
Requires-Python: >=3.10
License-File: LICENSE
Requires-Dist: requests>=2.32.0
Requires-Dist: lxml>=5.3.0
Requires-Dist: protego>=0.4.0
Requires-Dist: colorama>=0.4.6
Requires-Dist: selenium>=4.29.0
Dynamic: license-file
Dynamic: requires-python
